{
    "title": "FAQPage",
    "pageType": "innerpage",
    "content": [
        {
            "id": "FAQ-section",
            "section": "FAQ-section",
            "items": [
                {
                    "id": "FAQ-01",
                    "headings": [
                        {
                            "level": "h3",
                            "content": "HOW CAN I CONTACT THE TEAM FOR HELP?"
                        }
                    ],
                    "description": "If you need any help from our Team contact us via Email. "
                },
                {
                    "id": "FAQ-02",
                    "headings": [
                        {
                            "level": "h3",
                            "content": "What time will the tournament start in my country?"
                        }
                    ],
                    "description": "Tournaments are Timezoned to your Browser. So when the Time display on you 2pm is start on 2pm."
                },
                {
                    "id": "FAQ-03",
                    "headings": [
                        {
                            "level": "h3",
                            "content": "Can I play more then one Tournament per Day?"
                        }
                    ],
                    "description":"Yes you can play more then one Tournament per Day on our Website but its not allowed to play 2Tournaments at the same time because the delay to other Tournaments."
                },
                {
                    "id": "FAQ-04",
                    "headings": [
                        {
                            "level": "h3",
                            "content": "What Games are you supporting??"
                        }
                    ],
                    "description": "You can see all current games what we offer on the Games Site. "
                },
                {
                    "id": "FAQ-05",
                    "headings": [
                        {
                            "level": "h3",
                            "content": "How can I claim my prize?"
                        }
                    ],
                    "description": "When you won a Tournament, your prize will automatically be in your Wallet, the next day following your victory."
                },
                {
                    "id": "FAQ-06",
                    "headings": [
                        {
                            "level": "h3",
                            "content": "Where should I fill in my score, at the end of a match?"
                        }
                    ],
                    "description": "Once the match is over, you can fill in your score directly on the Website on the Match site. For a sure win, take a picture of your victory with the opponent's name and upload it to the website directly at the match page."
                },
                {
                    "id": "FAQ-07",
                    "headings": [
                        {
                            "level": "h3",
                            "content": "Is it possible to pause the OneUpGaming tournament?"
                        }
                    ],
                    "description": " desktop publishing software like including versions."
                }
            ]
        }
    ]
}
